<?xml version="1.0"?>
<root xmlns="urn:schemas-upnp-org:device-1-0">
<specVersion>
<major>1</major>
<minor>0</minor>
</specVersion>
<device>
<deviceType>urn:schemas-upnp-org:device:l2tpv3:1</deviceType>
<friendlyName>gateway</friendlyName>
<manufacturer>AVM Berlin</manufacturer>
<manufacturerURL>http://www.avm.de</manufacturerURL>
<modelDescription>FRITZ!Box 7590</modelDescription>
<modelName>FRITZ!Box 7590</modelName>
<modelNumber>avm</modelNumber>
<modelURL>http://www.avm.de</modelURL>
<UDN>uuid:95802409-bccb-40e7-8e6c-444E6D5F4C38</UDN>
<iconList>
<icon>
<mimetype>image/gif</mimetype>
<width>118</width>
<height>119</height>
<depth>8</depth>
<url>/ligd.gif</url>
</icon>
</iconList>
<serviceList>
<service>
<serviceType>urn:schemas-any-com:service:l2tpv3:1</serviceType>
<serviceId>urn:any-com:serviceId:l2tpv31</serviceId>
<controlURL>/upnp/control/l2tpv3</controlURL>
<eventSubURL>/upnp/control/l2tpv3</eventSubURL>
<SCPDURL>/l2tpv3SCPD.xml</SCPDURL>
</service>
</serviceList>
<presentationURL>http://fritz.box</presentationURL>
</device>
</root>
